algoliasearch/__init__.py
algoliasearch/abtesting/__init__.py
algoliasearch/abtesting/client.py
algoliasearch/abtesting/config.py
algoliasearch/abtesting/models/__init__.py
algoliasearch/abtesting/models/ab_test.py
algoliasearch/abtesting/models/ab_test_configuration.py
algoliasearch/abtesting/models/ab_test_response.py
algoliasearch/abtesting/models/ab_tests_variant.py
algoliasearch/abtesting/models/ab_tests_variant_search_params.py
algoliasearch/abtesting/models/add_ab_tests_request.py
algoliasearch/abtesting/models/add_ab_tests_variant.py
algoliasearch/abtesting/models/currency.py
algoliasearch/abtesting/models/effect_metric.py
algoliasearch/abtesting/models/empty_search.py
algoliasearch/abtesting/models/empty_search_filter.py
algoliasearch/abtesting/models/error_base.py
algoliasearch/abtesting/models/estimate_ab_test_request.py
algoliasearch/abtesting/models/estimate_ab_test_response.py
algoliasearch/abtesting/models/estimate_configuration.py
algoliasearch/abtesting/models/feature_filters.py
algoliasearch/abtesting/models/filter_effects.py
algoliasearch/abtesting/models/list_ab_tests_response.py
algoliasearch/abtesting/models/minimum_detectable_effect.py
algoliasearch/abtesting/models/outliers.py
algoliasearch/abtesting/models/outliers_filter.py
algoliasearch/abtesting/models/status.py
algoliasearch/abtesting/models/variant.py
algoliasearch/abtesting_v3/__init__.py
algoliasearch/abtesting_v3/client.py
algoliasearch/abtesting_v3/config.py
algoliasearch/abtesting_v3/models/__init__.py
algoliasearch/abtesting_v3/models/ab_test.py
algoliasearch/abtesting_v3/models/ab_test_configuration.py
algoliasearch/abtesting_v3/models/ab_test_response.py
algoliasearch/abtesting_v3/models/ab_tests_variant.py
algoliasearch/abtesting_v3/models/ab_tests_variant_search_params.py
algoliasearch/abtesting_v3/models/add_ab_tests_request.py
algoliasearch/abtesting_v3/models/add_ab_tests_variant.py
algoliasearch/abtesting_v3/models/create_metric.py
algoliasearch-4.35.4.dist-info/METADATA
algoliasearch-4.35.4.dist-info/WHEEL
algoliasearch-4.35.4.dist-info/licenses/LICENSE
algoliasearch-4.35.4.dist-info/RECORD
