Metadata-Version: 2.4
Name: algoliasearch
Version: 4.35.4
Summary: A fully-featured and blazing-fast Python API client to interact with Algolia.
License: MIT
License-File: LICENSE
Keywords: algolia,search,full-text-search,neural-search
Author: Algolia Team
Requires-Python: >=3.8.1
Classifier: Intended Audience :: Developers
Classifier: License :: OSI Approved :: MIT License
Classifier: Programming Language :: Python :: 3
Classifier: Programming Language :: Python :: 3.9
Classifier: Programming Language :: Python :: 3.10
Classifier: Programming Language :: Python :: 3.11
Classifier: Programming Language :: Python :: 3.12
Classifier: Programming Language :: Python :: 3.13
Classifier: Programming Language :: Python :: 3.14
Classifier: Topic :: Internet :: WWW/HTTP :: Indexing/Search
Requires-Dist: aiohttp (>=3.10.11)
Requires-Dist: async-timeout (>=4.0.3)
Requires-Dist: pydantic (>=2)
Requires-Dist: python-dateutil (>=2.8.2)
Requires-Dist: requests (>=2.32.3)
Requires-Dist: urllib3 (>=2.2.3)
Project-URL: Homepage, https://www.algolia.com
Project-URL: Repository, https://github.com/algolia/algoliasearch-client-python
